CTClustering/__init__.py
CTClustering/calcp.py
CTClustering/clustering.py
CTClustering/ctc.py
CTClustering/estimating.py
CTClustering/flow.py
CTClustering/jointdata.py
CTClustering/merging.py
ctclustering-0.1.0.dist-info/METADATA
ctclustering-0.1.0.dist-info/WHEEL
ctclustering-0.1.0.dist-info/top_level.txt
ctclustering-0.1.0.dist-info/RECORD
